[
  {
    "configName": "Etoilée",
    "tag": "29UPLG8QQ",
    "error": true,
    "errorMessage": "Failed to fetch 29UPLG8QQ: {\"reason\":\"accessDenied.invalidIp\",\"message\":\"Invalid authorization: API key does not allow access from IP 52.159.229.167\"}",
    "fetchedAt": "2026-04-29T05:15:03.595Z"
  },
  {
    "configName": "Fleurie",
    "tag": "2C9Y28JPP",
    "error": true,
    "errorMessage": "Failed to fetch 2C9Y28JPP: {\"reason\":\"accessDenied.invalidIp\",\"message\":\"Invalid authorization: API key does not allow access from IP 52.159.229.167\"}",
    "fetchedAt": "2026-04-29T05:15:03.620Z"
  },
  {
    "configName": "Celeste",
    "tag": "2JUVYQ0YV",
    "error": true,
    "errorMessage": "Failed to fetch 2JUVYQ0YV: {\"reason\":\"accessDenied.invalidIp\",\"message\":\"Invalid authorization: API key does not allow access from IP 52.159.229.167\"}",
    "fetchedAt": "2026-04-29T05:15:03.643Z"
  },
  {
    "configName": "Gelée",
    "tag": "2CJJLLUQ9",
    "error": true,
    "errorMessage": "Failed to fetch 2CJJLLUQ9: {\"reason\":\"accessDenied.invalidIp\",\"message\":\"Invalid authorization: API key does not allow access from IP 52.159.229.167\"}",
    "fetchedAt": "2026-04-29T05:15:03.667Z"
  }
]